LICENSE.txt
MANIFEST.in
README.md
package.py
setup.cfg
setup.py
requirements/requirements.txt
vatis/asr_commons/__init__.py
vatis/asr_commons/config/__init__.py
vatis/asr_commons/config/audio.py
vatis/asr_commons/config/headers.py
vatis/asr_commons/config/logging.py
vatis/asr_commons/config/models_config.py
vatis/asr_commons/config/parse.py
vatis/asr_commons/constants/__init__.py
vatis/asr_commons/constants/custom_models.py
vatis/asr_commons/custom_models/__init__.py
vatis/asr_commons/custom_models/en_GB.py
vatis/asr_commons/custom_models/model.py
vatis/asr_commons/custom_models/ro_RO.py
vatis/asr_commons/domain/__init__.py
vatis/asr_commons/domain/exception.py
vatis/asr_commons/domain/expression.py
vatis/asr_commons/domain/find_replace.py
vatis/asr_commons/domain/models_config.py
vatis/asr_commons/domain/speaker.py
vatis/asr_commons/domain/spoken_commands.py
vatis/asr_commons/domain/transcriber.py
vatis/asr_commons/domain/word.py
vatis/asr_commons/i18n/__init__.py
vatis/asr_commons/i18n/i18n_keys.py
vatis/asr_commons/i18n/translate.py
vatis/asr_commons/i18n/locale/speakers_service.pot
vatis/asr_commons/i18n/locale/en/LC_MESSAGES/speakers_service.mo
vatis/asr_commons/i18n/locale/en/LC_MESSAGES/speakers_service.po
vatis/asr_commons/i18n/locale/ro/LC_MESSAGES/speakers_service.mo
vatis/asr_commons/i18n/locale/ro/LC_MESSAGES/speakers_service.po
vatis/asr_commons/json/__init__.py
vatis/asr_commons/json/deserialization.py
vatis/asr_commons/json/serialization.py
vatis/asr_commons/live/__init__.py
vatis/asr_commons/live/event.py
vatis/asr_commons/live/headers.py
vatis/asr_commons/live/response.py
vatis/asr_commons/live/sio_topics.py
vatis/asr_commons/live/utils.py
vatis/asr_commons/scaler/__init__.py
vatis/asr_commons/scaler/response.py
vatis/asr_commons/security/__init__.py
vatis/asr_commons/security/jwt.py
vatis/asr_commons/static/__init__.py
vatis/asr_commons/static/exceptions.py
vatis/asr_commons/static/headers.py
vatis/asr_commons/static/request.py
vatis_asr_commons.egg-info/PKG-INFO
vatis_asr_commons.egg-info/SOURCES.txt
vatis_asr_commons.egg-info/dependency_links.txt
vatis_asr_commons.egg-info/namespace_packages.txt
vatis_asr_commons.egg-info/not-zip-safe
vatis_asr_commons.egg-info/requires.txt
vatis_asr_commons.egg-info/top_level.txt