Metadata-Version: 2.1
Name: vatis-asr-commons
Version: 2.0.6
Summary: Common objects for Vatis ASR clients
Home-page: https://gitlab.com/vatistech/asr-commons
Maintainer: VATIS TECH
Maintainer-email: support@vatis.tech
License: UNKNOWN
Download-URL: https://gitlab.com/vatistech/asr-commons/-/archive/2.0.6/asr_commons-2.0.6.zip
Platform: UNKNOWN
Classifier: Development Status :: 5 - Production/Stable
Classifier: Intended Audience :: Developers
Classifier: License :: OSI Approved :: Apache Software License
Classifier: Programming Language :: Python
Classifier: Programming Language :: Python :: 3
Classifier: Programming Language :: Python :: 3.8
Classifier: Programming Language :: Python :: 3.9
Classifier: Programming Language :: Python :: 3.10
Classifier: Operating System :: OS Independent
Classifier: Topic :: Software Development :: Build Tools
Classifier: Topic :: Internet
Requires-Python: >=3.8
License-File: LICENSE.txt
